[
  {
    "requiresRole":["app_organisaatiohallinta", "app_yksityisten_rekisteroityminen"],
    "key":"organisaatiot",
    "links":[
      {
        "key":"organisaatiotyllapito",
        "requiresRole":["app_organisaatiohallinta"],
        "href":"/organisaatio-service/organisaatiot"
      },
      {
        "key":"ryhmatyllapito",
        "requiresRole":["app_organisaatiohallinta"],
        "href":"/organisaatio-service/ryhmat"
      },
      {
        "key":"yksityistenrekisteroityminen",
        "requiresRole":["app_organisaatioiden_rekisteroityminen"],
        "href":"/varda-rekisterointi/virkailija"
      },
      {
        "key":"osoitepalvelu",
        "href":"/osoitekoostepalvelu/#/",
        "requiresRole":["app_osoite"]
      }
    ]
  },
  {
    "key":"jarjestelmanhallinta",
    "requiresRole":["app_valintaperusteet","app_valintojentoteuttaminen"],
    "links":[
      {
        "key":"kaytonhallintaanomukset",
        "href":"/henkilo-ui/henkilohaku",
        "requiresRole":["app_kayttooikeus_rekisterinpitaja", "app_oppijanumerorekisteri_oppijoidentuonti", "app_kayttooikeus_crud"]
      },
      {
        "key":"kaytonhallintaryhmat",
        "href":"/henkilo-ui/kayttooikeusryhmat",
        "requiresRole":["app_kayttooikeus_kayttooikeusryhmien_luku", "app_kayttooikeus_rekisterinpitaja"]
      },
      {
        "key":"palvelukayttajat",
        "href":"/henkilo-ui/palvelukayttaja",
        "requiresRole":["app_kayttooikeus_palvelukayttaja_crud", "app_kayttooikeus_rekisterinpitaja"]
      },
      {
        "key":"virkailijanluonti",
        "href":"/henkilo-ui/virkailija/luonti",
        "requiresRole":["app_kayttooikeus_virkailijanluonti"]
      },
      {
        "key":"kaytonhallintakoodisto",
        "href":"/koodisto-app/",
        "requiresRole":["app_koodisto"]
      },
      {
        "key":"kaytonhallintakaannokset",
        "href":"/lokalisointi/secured/index.html",
        "requiresRole":["app_lokalisointi_crud"]
      }
    ]

  },
  {
    "key":"eperusteet",
    "requiresRole":["app_eperusteet"],
    "links":[
      {
        "key":"eperusteet",
        "href":"/eperusteet-app/",
        "requiresRole":["app_eperusteet"]
      },
	  {
        "key":"eperusteet-laadinta",
        "href":"/eperusteet-app/uusi",
        "requiresRole":["app_eperusteet"]
      },
      {
        "key":"lops-tyokalu",
        "href":"/eperusteet-ylops-app/uusi",
        "requiresRole":["app_eperusteet_ylops"]
      },
      {
        "key":"amosaa-ops-ty\u00f6kalu",
        "href":"/eperusteet-amosaa-app/",
        "requiresRole":["app_eperusteet_amosaa"]
      },
	  {
        "key":"amosaa-ops-tyokalu-uusi",
        "href":"/eperusteet-amosaa-app/uusi/#/ammatillinen",
        "requiresRole":["app_eperusteet_amosaa_new"]
      },
	  {
        "key":"vst-tyokalu",
        "href":"/eperusteet-amosaa-app/uusi/#/vapaasivistystyo",
        "requiresRole":["app_eperusteet_vst"]
      },
	  {
        "key":"tuva-tyokalu",
        "href":"/eperusteet-amosaa-app/uusi/#/tutkintoonvalmentava",
        "requiresRole":["app_eperusteet_tuva"]
      },
	  {
        "key":"koto-tyokalu",
        "href":"/eperusteet-amosaa-app/uusi/#/kotoutumiskoulutus",
        "requiresRole":["app_eperusteet_koto"]
      }
    ]

  },
  {
    "key":"koulutustarjonta",
    "requiresRole":["app_tarjonta", "app_kouta"],
    "links":[
      {
        "key":"kouta",
        "href":"/kouta",
        "requiresRole":["app_kouta"]
      },
      {
        "key":"tarjontakoulutuksetjahaut",
        "href":"/tarjonta-app/index.html",
        "requiresRole":["app_tarjonta"]
      },
      {
        "key":"hautyllapito",
        "href":"/tarjonta-app/index.html#/haku",
        "requiresRole":["app_hakujenhallinta"]
      },
      {
        "key":"tarjontavalinnat",
        "href":"/tarjonta-app/index.html#/valintaPerusteKuvaus/search",
        "requiresRole":["app_valintaperustekuvaustenhallinta","app_valintaperustekuvaustenhallinta_kk"]
      }
    ]
  },
  {
    "key":"hakemuksetjavalinnat",
    "requiresRole":["app_hakemus", "app_valintojentoteuttaminen", "app_valintaperusteet", "app_ataru", "app_hakukohderyhmapalvelu"],
    "links":[
      {
        "key":"ataruhakija",
        "href":"/lomake-editori/applications",
        "requiresRole":["app_ataru_hakemus"]
      },
      {
        "key":"atarueditori",
        "href":"/lomake-editori/",
        "requiresRole":["app_ataru_editori"]
      },
      {
        "key":"hakukohderyhmapalvelu",
        "href":"/hakukohderyhmapalvelu/hakukohderyhmien-hallinta",
        "requiresRole":["app_hakukohderyhmapalvelu"]
      },
      {
        "key":"valinnattoteuttaminen",
        "href":"/valintalaskenta-ui/",
        "requiresRole":["app_valintojentoteuttaminen"]
      },
      {
        "key":"valinnatperusteet",
        "href":"/valintaperusteet-ui/",
        "requiresRole":["app_valintaperusteet"]
      },
      {
        "key":"valintajononhallinta",
        "href":"/valintalaskenta-ui/app/jono/hallinta.html",
        "requiresRole":["app_valintojentoteuttaminen_crud_1.2.246.562.10.00000000001","app_valintojentoteuttaminenkk_crud"]
      },
      {
        "key":"hakulomakkeenhallinta",
        "href":"/hakulomakkeenhallinta-ui/app/index.html#/applicationSystemForm",
        "requiresRole":["app_hakemus"]
      },
      {
        "key":"hauthakemukset",
        "href":"/haku-app/virkailija/hakemus",
        "requiresRole":["app_hakemus"]
      }
    ]
  },
  {
    "key":"raportointi_ja_viestinta",
    "requiresRole":["app_raportointi","app_ryhmasahkoposti","app_asiakirjapalvelu"],
    "links":[
      {
        "key":"raportointi",
        "href":"/virkailija-raamit/virkailija-raamit/raportointi.html",
        "requiresRole":["app_raportointi"]
      },
      {
        "key":"kirje_raportointi",
        "href":"/viestintapalvelu-ui/#/reportLetters",
        "requiresRole":["app_asiakirjapalvelu"]
      },
      {
        "key":"email_raportointi",
        "href":"/viestintapalvelu-ui/#/reportMessages/list",
        "requiresRole":["app_ryhmasahkoposti"]
      },
      {
        "key":"kirje_kirjepohjat",
        "href":"/viestintapalvelu-ui/#/letter-templates",
        "requiresRole":["app_asiakirjapalvelu_create_template"]
      }
    ]
  },
  {
    "key":"rekisterit",
    "requiresRole":["app_tiedonsiirto","app_suoritusrekisteri","app_koski","app_varda", "app_ehoks", "app_valpas", "app_mpassid"],
    "links":[
      {
        "key":"koski",
        "href":"/koski/virkailija",
        "requiresRole":["app_koski"]
      },
      {
        "key":"rekisteritsuoritusrekisteri",
        "href":"/suoritusrekisteri/#/",
        "requiresRole":["app_suoritusrekisteri_read","app_suoritusrekisteri_read_update","app_suoritusrekisteri_crud"]
      },
      {
        "key":"rekisterittiedonsiirrot",
        "href":"/suoritusrekisteri/#/tiedonsiirto",
        "requiresRole":["app_tiedonsiirto"]
      },
      {
        "key":"varda",
        "href":"/varda",
        "requiresRole":["app_varda"]
      },
      {
        "key":"ehoks",
        "href":"/ehoks-virkailija-ui",
        "requiresRole":["app_ehoks_read", "app_ehoks_crud", "app_ehoks_ophpaakayttaja"]
      },
      {
        "key":"valpas",
        "href":"/valpas/virkailija",
        "requiresRole":["app_valpas"]
      },
      {
        "key":"mpassid",
        "href":"/mpassid",
        "requiresRole":["app_mpassid"]
      }
    ]
  },
  {
    "key":"aitu",
    "href":"/aitu/",
    "requiresRole":["app_aitu"]
  },
  {
    "key":"aipal",
    "href":"/aipal/",
    "requiresRole":["app_aipal"]
  },
  {
    "key":"arvo",
    "href":"https://arvo.csc.fi/",
    "testHref":" http://testarvo.csc.fi/",
    "target":"_blank",
    "requiresRole":["app_amkpal"]
  },
  {
    "key":"valssi",
    "href":"https://valssi.karvi.fi/",
    "testHref":"https://qa-valssi.karvi.fi/",
    "target":"_blank",
    "requiresRole":["app_valssi"]
  },
  {
    "key":"kieli-ja-kaantaja-tutkinnot",
    "requiresRole":["app_akt", "app_oikeustulkkirekisteri_oikeustulkki_crud", "app_vkt"],
    "links":[
      {
        "key":"akr",
        "href":"/akr/virkailija",
        "requiresRole":["app_akt"]
      },
      {
        "key":"otr",
        "href":"/otr/virkailija",
        "requiresRole":["app_oikeustulkkirekisteri_oikeustulkki_crud"]
      },
      {
        "key":"vkt",
        "href":"/vkt/virkailija",
        "requiresRole":["app_vkt"]
      }
    ]
  },
  {
    "key":"yki",
    "requiresRole":["app_yki_yllapitaja","app_yki_jarjestaja"],
    "links":[
      {
        "key":"jarjestajarekisteri",
        "href":"/yki/auth/cas",
        "requiresRole":["app_yki_yllapitaja"]
      },
      {
        "key":"tutkintotilaisuudet",
        "href":"/yki/auth/cas",
        "requiresRole":["app_yki_jarjestaja"]
      },
      {
        "key":"maksuraportit",
        "href":"/yki/auth/cas",
        "requiresRole":["app_yki_yllapitaja"]
      }
    ]
  }
]
